LICENSE
README.md
setup.cfg
setup.py
NanDealer/NanHandler.py
NanDealer/__init__.py
NanDealer.egg-info/PKG-INFO
NanDealer.egg-info/SOURCES.txt
NanDealer.egg-info/dependency_links.txt
NanDealer.egg-info/top_level.txt