Metadata-Version: 2.1
Name: NanDealer
Version: 1.0.1
Summary: A library which can deal with Nan values in a dataframe
Home-page: https://github.com/iamatul1214/NanDealer
Author: Atul Rai
Author-email: iamatul1214@gmail.com
License: MIT
Platform: UNKNOWN
Classifier: Programming Language :: Python :: 3.8
Classifier: Intended Audience :: Developers
Classifier: License :: OSI Approved :: MIT License
License-File: LICENSE
